{
  "name" : "b502",
  "application" : "bg",
  "description" : "ΧΡΕΩΣΗ ΛΟΓΑΡΙΑΣΜΟΥ ΜΕ ΕΠΙΤΑΓΗ",
  "inputRecordName" : "bgm502",
  "sgAsPa" : false,
  "blankPaDiscarded" : false,
  "records" : {
    "bgm502" : {
      "name" : "bgm502",
      "transactionName" : "b502",
      "description" : "PENSION WITHDRAWAL",
      "type" : "Input",
      "source" : "FDF",
      "fields" : {
        "ccc" : {
          "name" : "ccc",
          "index" : 1,
          "offset" : 16,
          "literal" : "CLIENT ACCOUNT CODE",
          "type" : "Alphanumeric",
          "length" : 20,
          "scale" : 0,
          "delimiter" : 1,
          "usage" : "Required",
          "debug" : true,
          "debugger" : "BR6CNEW0",
          "alwaysSent" : false,
          "compressed" : true
        },
        "sallib" : {
          "name" : "sallib",
          "index" : 2,
          "offset" : 39,
          "literal" : "PASSBOOK BALANCE",
          "type" : "EditSign",
          "length" : 17,
          "scale" : 2,
          "delimiter" : 2,
          "usage" : "Required",
          "debug" : false,
          "alwaysSent" : false,
          "compressed" : true
        },
        "linea" : {
          "name" : "linea",
          "index" : 3,
          "offset" : 59,
          "literal" : "LINE",
          "type" : "Numeric",
          "length" : 2,
          "scale" : 0,
          "delimiter" : 3,
          "usage" : "Required",
          "debug" : false,
          "alwaysSent" : false,
          "compressed" : true
        },
        "numdoc" : {
          "name" : "numdoc",
          "index" : 4,
          "offset" : 64,
          "literal" : "DOCUMENT NUMBER",
          "type" : "Alphanumeric",
          "length" : 3,
          "scale" : 0,
          "delimiter" : 4,
          "usage" : "Required",
          "debug" : false,
          "alwaysSent" : false,
          "compressed" : true
        },
        "contviv" : {
          "name" : "contviv",
          "index" : 5,
          "offset" : 70,
          "literal" : "EXPER. CONTROL ACT.",
          "type" : "Alphanumeric",
          "length" : 1,
          "scale" : 0,
          "delimiter" : 5,
          "usage" : "Optional",
          "debug" : false,
          "alwaysSent" : false,
          "compressed" : true
        },
        "codiest" : {
          "name" : "codiest",
          "index" : 6,
          "offset" : 74,
          "literal" : "STATISTIC CODE",
          "type" : "Alphanumeric",
          "length" : 6,
          "scale" : 0,
          "delimiter" : 6,
          "usage" : "Optional",
          "debug" : false,
          "alwaysSent" : false,
          "compressed" : true
        },
        "codpais" : {
          "name" : "codpais",
          "index" : 7,
          "offset" : 83,
          "literal" : "COUNTRY CODE",
          "type" : "Alphanumeric",
          "length" : 3,
          "scale" : 0,
          "delimiter" : 7,
          "usage" : "Optional",
          "debug" : false,
          "alwaysSent" : false,
          "compressed" : true
        },
        "banda" : {
          "name" : "banda",
          "index" : 8,
          "offset" : 89,
          "literal" : "STRIP",
          "type" : "Alphanumeric",
          "length" : 1,
          "scale" : 0,
          "delimiter" : -80,
          "usage" : "Optional",
          "debug" : false,
          "alwaysSent" : false,
          "compressed" : true
        },
        "libre" : {
          "name" : "libre",
          "index" : 9,
          "offset" : 93,
          "literal" : "FREE",
          "type" : "Alphanumeric",
          "length" : 12,
          "scale" : 0,
          "delimiter" : 8,
          "usage" : "Optional",
          "debug" : false,
          "alwaysSent" : false,
          "compressed" : true
        }
      }
    }
  }
}