{
  "name" : "bcof",
  "application" : "bg",
  "description" : "COST OF FUNDS DYNAMIC REPORT",
  "inputRecordName" : "bgmcos",
  "sgAsPa" : false,
  "blankPaDiscarded" : false,
  "records" : {
    "bgmcos" : {
      "name" : "bgmcos",
      "transactionName" : "bcof",
      "description" : "FORMAT FOR THE BCOF TRANS",
      "type" : "InputOutput",
      "source" : "FDF",
      "fields" : {
        "prodfro" : {
          "name" : "prodfro",
          "index" : 1,
          "offset" : 16,
          "literal" : "PRODUCT FROM",
          "type" : "Alphanumeric",
          "length" : 2,
          "scale" : 0,
          "delimiter" : 7,
          "usage" : "Required",
          "debug" : false,
          "alwaysSent" : true,
          "compressed" : true
        },
        "prodto" : {
          "name" : "prodto",
          "index" : 2,
          "offset" : 21,
          "literal" : "PRODUCT TO",
          "type" : "Alphanumeric",
          "length" : 2,
          "scale" : 0,
          "delimiter" : 8,
          "usage" : "Required",
          "debug" : false,
          "alwaysSent" : true,
          "compressed" : true
        },
        "subpfro" : {
          "name" : "subpfro",
          "index" : 3,
          "offset" : 26,
          "literal" : "SUBPROD FROM",
          "type" : "Alphanumeric",
          "length" : 4,
          "scale" : 0,
          "delimiter" : 9,
          "usage" : "Optional",
          "debug" : false,
          "alwaysSent" : true,
          "compressed" : true
        },
        "subpto" : {
          "name" : "subpto",
          "index" : 4,
          "offset" : 33,
          "literal" : "SUBPROD TO",
          "type" : "Alphanumeric",
          "length" : 4,
          "scale" : 0,
          "delimiter" : 10,
          "usage" : "Optional",
          "debug" : false,
          "alwaysSent" : true,
          "compressed" : true
        },
        "tarfrom" : {
          "name" : "tarfrom",
          "index" : 5,
          "offset" : 40,
          "literal" : "TARIFF FROM",
          "type" : "Alphanumeric",
          "length" : 4,
          "scale" : 0,
          "delimiter" : 11,
          "usage" : "Optional",
          "debug" : false,
          "alwaysSent" : true,
          "compressed" : true
        },
        "tarto" : {
          "name" : "tarto",
          "index" : 6,
          "offset" : 47,
          "literal" : "TARIFF TO",
          "type" : "Alphanumeric",
          "length" : 4,
          "scale" : 0,
          "delimiter" : 12,
          "usage" : "Optional",
          "debug" : false,
          "alwaysSent" : true,
          "compressed" : true
        },
        "perfrom" : {
          "name" : "perfrom",
          "index" : 7,
          "offset" : 54,
          "literal" : "PERIODICITY FROM",
          "type" : "Alphanumeric",
          "length" : 1,
          "scale" : 0,
          "delimiter" : 2,
          "usage" : "Optional",
          "debug" : false,
          "alwaysSent" : true,
          "compressed" : true
        },
        "perto" : {
          "name" : "perto",
          "index" : 8,
          "offset" : 58,
          "literal" : "PERIODICITY TO",
          "type" : "Alphanumeric",
          "length" : 1,
          "scale" : 0,
          "delimiter" : 3,
          "usage" : "Optional",
          "debug" : false,
          "alwaysSent" : true,
          "compressed" : true
        },
        "monthfr" : {
          "name" : "monthfr",
          "index" : 9,
          "offset" : 62,
          "literal" : "MONTH FROM",
          "type" : "Alphanumeric",
          "length" : 2,
          "scale" : 0,
          "delimiter" : 13,
          "usage" : "Required",
          "debug" : false,
          "alwaysSent" : true,
          "compressed" : true
        },
        "yearfro" : {
          "name" : "yearfro",
          "index" : 10,
          "offset" : 67,
          "literal" : "YEAR FROM",
          "type" : "Alphanumeric",
          "length" : 4,
          "scale" : 0,
          "delimiter" : 14,
          "usage" : "Required",
          "debug" : false,
          "alwaysSent" : true,
          "compressed" : true
        },
        "monthto" : {
          "name" : "monthto",
          "index" : 11,
          "offset" : 74,
          "literal" : "MONTH TO",
          "type" : "Alphanumeric",
          "length" : 2,
          "scale" : 0,
          "delimiter" : 15,
          "usage" : "Required",
          "debug" : false,
          "alwaysSent" : true,
          "compressed" : true
        },
        "yearto" : {
          "name" : "yearto",
          "index" : 12,
          "offset" : 79,
          "literal" : "YEAR TO",
          "type" : "Alphanumeric",
          "length" : 4,
          "scale" : 0,
          "delimiter" : 16,
          "usage" : "Required",
          "debug" : false,
          "alwaysSent" : true,
          "compressed" : true
        },
        "currenc" : {
          "name" : "currenc",
          "index" : 13,
          "offset" : 86,
          "literal" : "CURRENCY",
          "type" : "Alphanumeric",
          "length" : 3,
          "scale" : 0,
          "delimiter" : -128,
          "usage" : "Required",
          "debug" : false,
          "alwaysSent" : true,
          "compressed" : true
        },
        "scale1f" : {
          "name" : "scale1f",
          "index" : 14,
          "offset" : 92,
          "literal" : "SCALE 1 FROM",
          "type" : "Alphanumeric",
          "length" : 17,
          "scale" : 0,
          "delimiter" : 17,
          "usage" : "Optional",
          "debug" : false,
          "alwaysSent" : true,
          "compressed" : true
        },
        "scale1t" : {
          "name" : "scale1t",
          "index" : 15,
          "offset" : 112,
          "literal" : "SCALE 1 TO",
          "type" : "Alphanumeric",
          "length" : 17,
          "scale" : 0,
          "delimiter" : 18,
          "usage" : "Optional",
          "debug" : false,
          "alwaysSent" : true,
          "compressed" : true
        },
        "scale2f" : {
          "name" : "scale2f",
          "index" : 16,
          "offset" : 132,
          "literal" : "SCALE 2 FROM",
          "type" : "Alphanumeric",
          "length" : 17,
          "scale" : 0,
          "delimiter" : 19,
          "usage" : "Optional",
          "debug" : false,
          "alwaysSent" : true,
          "compressed" : true
        },
        "scale2t" : {
          "name" : "scale2t",
          "index" : 17,
          "offset" : 152,
          "literal" : "SCALE 2 TO",
          "type" : "Alphanumeric",
          "length" : 17,
          "scale" : 0,
          "delimiter" : 20,
          "usage" : "Optional",
          "debug" : false,
          "alwaysSent" : true,
          "compressed" : true
        },
        "scale3f" : {
          "name" : "scale3f",
          "index" : 18,
          "offset" : 172,
          "literal" : "SCALE 3 FROM",
          "type" : "Alphanumeric",
          "length" : 17,
          "scale" : 0,
          "delimiter" : 21,
          "usage" : "Optional",
          "debug" : false,
          "alwaysSent" : true,
          "compressed" : true
        },
        "scale3t" : {
          "name" : "scale3t",
          "index" : 19,
          "offset" : 192,
          "literal" : "SCALE 3 TO",
          "type" : "Alphanumeric",
          "length" : 17,
          "scale" : 0,
          "delimiter" : 22,
          "usage" : "Optional",
          "debug" : false,
          "alwaysSent" : true,
          "compressed" : true
        },
        "scale4f" : {
          "name" : "scale4f",
          "index" : 20,
          "offset" : 212,
          "literal" : "SCALE 4 FROM",
          "type" : "Alphanumeric",
          "length" : 17,
          "scale" : 0,
          "delimiter" : 23,
          "usage" : "Optional",
          "debug" : false,
          "alwaysSent" : true,
          "compressed" : true
        },
        "scale4t" : {
          "name" : "scale4t",
          "index" : 21,
          "offset" : 232,
          "literal" : "SCALE 4 TO",
          "type" : "Alphanumeric",
          "length" : 17,
          "scale" : 0,
          "delimiter" : 24,
          "usage" : "Optional",
          "debug" : false,
          "alwaysSent" : true,
          "compressed" : true
        },
        "scale5f" : {
          "name" : "scale5f",
          "index" : 22,
          "offset" : 252,
          "literal" : "SCALE 5 FROM",
          "type" : "Alphanumeric",
          "length" : 17,
          "scale" : 0,
          "delimiter" : 25,
          "usage" : "Optional",
          "debug" : false,
          "alwaysSent" : true,
          "compressed" : true
        },
        "scale5t" : {
          "name" : "scale5t",
          "index" : 23,
          "offset" : 272,
          "literal" : "SCALE 5 TO",
          "type" : "Alphanumeric",
          "length" : 17,
          "scale" : 0,
          "delimiter" : 26,
          "usage" : "Optional",
          "debug" : false,
          "alwaysSent" : true,
          "compressed" : true
        },
        "scale6f" : {
          "name" : "scale6f",
          "index" : 24,
          "offset" : 292,
          "literal" : "SCALE 6 FROM",
          "type" : "Alphanumeric",
          "length" : 17,
          "scale" : 0,
          "delimiter" : 27,
          "usage" : "Optional",
          "debug" : false,
          "alwaysSent" : true,
          "compressed" : true
        },
        "scale6t" : {
          "name" : "scale6t",
          "index" : 25,
          "offset" : 312,
          "literal" : "SCALE 6 TO",
          "type" : "Alphanumeric",
          "length" : 17,
          "scale" : 0,
          "delimiter" : 127,
          "usage" : "Optional",
          "debug" : false,
          "alwaysSent" : true,
          "compressed" : true
        },
        "scale7f" : {
          "name" : "scale7f",
          "index" : 26,
          "offset" : 332,
          "literal" : "SCALE 7 FROM",
          "type" : "Alphanumeric",
          "length" : 17,
          "scale" : 0,
          "delimiter" : -127,
          "usage" : "Optional",
          "debug" : false,
          "alwaysSent" : true,
          "compressed" : true
        },
        "scale7t" : {
          "name" : "scale7t",
          "index" : 27,
          "offset" : 352,
          "literal" : "SCALE 7 TO",
          "type" : "Alphanumeric",
          "length" : 17,
          "scale" : 0,
          "delimiter" : -126,
          "usage" : "Optional",
          "debug" : false,
          "alwaysSent" : true,
          "compressed" : true
        },
        "scale8f" : {
          "name" : "scale8f",
          "index" : 28,
          "offset" : 372,
          "literal" : "SCALE 8 FROM",
          "type" : "Alphanumeric",
          "length" : 17,
          "scale" : 0,
          "delimiter" : -125,
          "usage" : "Optional",
          "debug" : false,
          "alwaysSent" : true,
          "compressed" : true
        },
        "scale8t" : {
          "name" : "scale8t",
          "index" : 29,
          "offset" : 392,
          "literal" : "SCALE 8 TO",
          "type" : "Alphanumeric",
          "length" : 17,
          "scale" : 0,
          "delimiter" : -124,
          "usage" : "Optional",
          "debug" : false,
          "alwaysSent" : true,
          "compressed" : true
        }
      }
    }
  }
}