{
  "name" : "mp29",
  "application" : "mp",
  "description" : "APPLIC. PROCESSING CHECKING",
  "inputRecordName" : "mprm290",
  "sgAsPa" : false,
  "blankPaDiscarded" : false,
  "records" : {
    "mprm290" : {
      "name" : "mprm290",
      "transactionName" : "mp29",
      "description" : "APPLIC. PROCESSING CHECKING",
      "type" : "InputOutput",
      "source" : "FDF",
      "fields" : {
        "mcncota" : {
          "name" : "mcncota",
          "index" : 1,
          "offset" : 16,
          "literal" : "CONTRACT NUMBER",
          "type" : "Alphanumeric",
          "length" : 20,
          "scale" : 0,
          "delimiter" : 1,
          "usage" : "Optional",
          "debug" : true,
          "debugger" : "MR6CSEC0",
          "alwaysSent" : true,
          "compressed" : true
        },
        "mcmnota" : {
          "name" : "mcmnota",
          "index" : 2,
          "offset" : 39,
          "literal" : "MAIN HOLDER",
          "type" : "Alphanumeric",
          "length" : 30,
          "scale" : 0,
          "delimiter" : 2,
          "usage" : "Optional",
          "debug" : false,
          "alwaysSent" : true,
          "compressed" : true
        },
        "mcinumc" : {
          "name" : "mcinumc",
          "index" : 3,
          "offset" : 72,
          "literal" : "CUSTOMER NUMBER",
          "type" : "Alphanumeric",
          "length" : 8,
          "scale" : 0,
          "delimiter" : 3,
          "usage" : "Optional",
          "debug" : false,
          "alwaysSent" : true,
          "compressed" : true
        },
        "mcyfast" : {
          "name" : "mcyfast",
          "index" : 4,
          "offset" : 83,
          "literal" : "FAST CREDIT",
          "type" : "Alphanumeric",
          "length" : 1,
          "scale" : 0,
          "delimiter" : 22,
          "usage" : "Optional",
          "debug" : false,
          "alwaysSent" : true,
          "compressed" : true
        },
        "ngrprd" : {
          "name" : "ngrprd",
          "index" : 5,
          "offset" : 87,
          "literal" : "GRACE PERIOD",
          "type" : "Numeric",
          "length" : 3,
          "scale" : 0,
          "delimiter" : 27,
          "usage" : "Optional",
          "debug" : false,
          "alwaysSent" : false,
          "compressed" : false
        },
        "mcyhist" : {
          "name" : "mcyhist",
          "index" : 6,
          "offset" : 93,
          "literal" : "BANK HISTORY",
          "type" : "Alphanumeric",
          "length" : 1,
          "scale" : 0,
          "delimiter" : 4,
          "usage" : "Optional",
          "debug" : false,
          "alwaysSent" : true,
          "compressed" : true
        },
        "mcyalld" : {
          "name" : "mcyalld",
          "index" : 7,
          "offset" : 97,
          "literal" : "ALL DOCUMENTS",
          "type" : "Alphanumeric",
          "length" : 1,
          "scale" : 0,
          "delimiter" : 8,
          "usage" : "Optional",
          "debug" : false,
          "alwaysSent" : true,
          "compressed" : true
        },
        "csiamou" : {
          "name" : "csiamou",
          "index" : 8,
          "offset" : 101,
          "literal" : "CREDIT SCORING",
          "type" : "Numeric",
          "length" : 11,
          "scale" : 0,
          "delimiter" : 6,
          "usage" : "Optional",
          "debug" : false,
          "alwaysSent" : true,
          "compressed" : true
        },
        "mcyotec" : {
          "name" : "mcyotec",
          "index" : 9,
          "offset" : 115,
          "literal" : "OTE",
          "type" : "Alphanumeric",
          "length" : 1,
          "scale" : 0,
          "delimiter" : 9,
          "usage" : "Optional",
          "debug" : false,
          "alwaysSent" : true,
          "compressed" : true
        },
        "mcyambu" : {
          "name" : "mcyambu",
          "index" : 10,
          "offset" : 119,
          "literal" : "AM BUREAU",
          "type" : "Alphanumeric",
          "length" : 1,
          "scale" : 0,
          "delimiter" : 5,
          "usage" : "Optional",
          "debug" : false,
          "alwaysSent" : true,
          "compressed" : true
        },
        "mcytire" : {
          "name" : "mcytire",
          "index" : 11,
          "offset" : 123,
          "literal" : "TYRESIAS",
          "type" : "Alphanumeric",
          "length" : 1,
          "scale" : 0,
          "delimiter" : 10,
          "usage" : "Optional",
          "debug" : false,
          "alwaysSent" : true,
          "compressed" : true
        },
        "mcyvisa" : {
          "name" : "mcyvisa",
          "index" : 12,
          "offset" : 127,
          "literal" : "VISA",
          "type" : "Alphanumeric",
          "length" : 1,
          "scale" : 0,
          "delimiter" : 7,
          "usage" : "Optional",
          "debug" : false,
          "alwaysSent" : true,
          "compressed" : true
        },
        "cymello" : {
          "name" : "cymello",
          "index" : 13,
          "offset" : 131,
          "literal" : "MELLON BUREAU",
          "type" : "Alphanumeric",
          "length" : 1,
          "scale" : 0,
          "delimiter" : 23,
          "usage" : "Optional",
          "debug" : false,
          "alwaysSent" : true,
          "compressed" : true
        },
        "ilmcre" : {
          "name" : "ilmcre",
          "index" : 14,
          "offset" : 135,
          "literal" : "CREDIT LIMIT",
          "type" : "Numeric",
          "length" : 11,
          "scale" : 2,
          "delimiter" : 11,
          "usage" : "Optional",
          "debug" : false,
          "alwaysSent" : true,
          "compressed" : true
        },
        "ilcrea" : {
          "name" : "ilcrea",
          "index" : 15,
          "offset" : 149,
          "literal" : "PREVIOUS CREDIT",
          "type" : "Numeric",
          "length" : 11,
          "scale" : 2,
          "delimiter" : 12,
          "usage" : "Optional",
          "debug" : false,
          "alwaysSent" : true,
          "compressed" : true
        },
        "ilmcrt" : {
          "name" : "ilmcrt",
          "index" : 16,
          "offset" : 163,
          "literal" : "TEMPORAL CREDIT LIMI",
          "type" : "Numeric",
          "length" : 11,
          "scale" : 2,
          "delimiter" : 14,
          "usage" : "Optional",
          "debug" : false,
          "alwaysSent" : true,
          "compressed" : true
        },
        "ilimpe" : {
          "name" : "ilimpe",
          "index" : 17,
          "offset" : 177,
          "literal" : "CREDIT LIMI",
          "type" : "Numeric",
          "length" : 11,
          "scale" : 2,
          "delimiter" : 15,
          "usage" : "Optional",
          "debug" : false,
          "alwaysSent" : true,
          "compressed" : true
        },
        "fficra" : {
          "name" : "fficra",
          "index" : 18,
          "offset" : 191,
          "literal" : "VALID UNTIL",
          "type" : "Alphanumeric",
          "length" : 6,
          "scale" : 0,
          "delimiter" : 16,
          "usage" : "Optional",
          "debug" : false,
          "alwaysSent" : true,
          "compressed" : true
        },
        "fficrt" : {
          "name" : "fficrt",
          "index" : 19,
          "offset" : 200,
          "literal" : "VALID UNTIL",
          "type" : "Alphanumeric",
          "length" : 6,
          "scale" : 0,
          "delimiter" : 17,
          "usage" : "Optional",
          "debug" : false,
          "alwaysSent" : true,
          "compressed" : true
        },
        "ilcaad" : {
          "name" : "ilcaad",
          "index" : 20,
          "offset" : 209,
          "literal" : "CASH ADVANCE LIMIT",
          "type" : "Numeric",
          "length" : 11,
          "scale" : 2,
          "delimiter" : 21,
          "usage" : "Optional",
          "debug" : false,
          "alwaysSent" : true,
          "compressed" : true
        },
        "mctreas" : {
          "name" : "mctreas",
          "index" : 21,
          "offset" : 223,
          "literal" : "PENDING/REJECTION",
          "type" : "Alphanumeric",
          "length" : 2,
          "scale" : 0,
          "delimiter" : 18,
          "usage" : "Optional",
          "debug" : false,
          "alwaysSent" : true,
          "compressed" : true
        },
        "mctdesc" : {
          "name" : "mctdesc",
          "index" : 22,
          "offset" : 228,
          "literal" : "DESCRITPION REASON",
          "type" : "Alphanumeric",
          "length" : 15,
          "scale" : 0,
          "delimiter" : 19,
          "usage" : "Optional",
          "debug" : false,
          "alwaysSent" : true,
          "compressed" : true
        },
        "mcyflag" : {
          "name" : "mcyflag",
          "index" : 23,
          "offset" : 246,
          "literal" : "REASON FLAG",
          "type" : "Alphanumeric",
          "length" : 1,
          "scale" : 0,
          "delimiter" : 26,
          "usage" : "Optional",
          "debug" : false,
          "alwaysSent" : true,
          "compressed" : true
        },
        "mctoffc" : {
          "name" : "mctoffc",
          "index" : 24,
          "offset" : 250,
          "literal" : "CREDIT OFFICER",
          "type" : "Alphanumeric",
          "length" : 8,
          "scale" : 0,
          "delimiter" : 20,
          "usage" : "Optional",
          "debug" : false,
          "alwaysSent" : true,
          "compressed" : true
        }
      }
    },
    "mprm029" : {
      "name" : "mprm029",
      "transactionName" : "mp29",
      "description" : "CARD CREDIT APPROVAL",
      "type" : "InputOutput",
      "source" : "FDF",
      "fields" : {
        "mcncota" : {
          "name" : "mcncota",
          "index" : 1,
          "offset" : 16,
          "literal" : "CONTRACT NUMBER",
          "type" : "Alphanumeric",
          "length" : 20,
          "scale" : 0,
          "delimiter" : 1,
          "usage" : "Optional",
          "debug" : false,
          "alwaysSent" : true,
          "compressed" : true
        },
        "mcmnota" : {
          "name" : "mcmnota",
          "index" : 2,
          "offset" : 39,
          "literal" : "MAIN HOLDER",
          "type" : "Alphanumeric",
          "length" : 30,
          "scale" : 0,
          "delimiter" : 2,
          "usage" : "Optional",
          "debug" : false,
          "alwaysSent" : true,
          "compressed" : true
        },
        "mcinumc" : {
          "name" : "mcinumc",
          "index" : 3,
          "offset" : 72,
          "literal" : "CUSTOMER NUMBER",
          "type" : "Alphanumeric",
          "length" : 8,
          "scale" : 0,
          "delimiter" : 3,
          "usage" : "Optional",
          "debug" : false,
          "alwaysSent" : true,
          "compressed" : true
        },
        "mcyfast" : {
          "name" : "mcyfast",
          "index" : 4,
          "offset" : 83,
          "literal" : "FAST CREDIT",
          "type" : "Alphanumeric",
          "length" : 1,
          "scale" : 0,
          "delimiter" : 22,
          "usage" : "Optional",
          "debug" : false,
          "alwaysSent" : true,
          "compressed" : true
        },
        "mcyhist" : {
          "name" : "mcyhist",
          "index" : 5,
          "offset" : 87,
          "literal" : "BANK HISTORY",
          "type" : "Alphanumeric",
          "length" : 1,
          "scale" : 0,
          "delimiter" : 4,
          "usage" : "Optional",
          "debug" : false,
          "alwaysSent" : true,
          "compressed" : true
        },
        "mcyalld" : {
          "name" : "mcyalld",
          "index" : 6,
          "offset" : 91,
          "literal" : "ALL DOCUMENTS",
          "type" : "Alphanumeric",
          "length" : 1,
          "scale" : 0,
          "delimiter" : 8,
          "usage" : "Optional",
          "debug" : false,
          "alwaysSent" : true,
          "compressed" : true
        },
        "csiamou" : {
          "name" : "csiamou",
          "index" : 7,
          "offset" : 95,
          "literal" : "CREDIT SCORING",
          "type" : "Numeric",
          "length" : 11,
          "scale" : 2,
          "delimiter" : 6,
          "usage" : "Optional",
          "debug" : false,
          "alwaysSent" : true,
          "compressed" : true
        },
        "mcyotec" : {
          "name" : "mcyotec",
          "index" : 8,
          "offset" : 109,
          "literal" : "OTE",
          "type" : "Alphanumeric",
          "length" : 1,
          "scale" : 0,
          "delimiter" : 9,
          "usage" : "Optional",
          "debug" : false,
          "alwaysSent" : true,
          "compressed" : true
        },
        "mcyambu" : {
          "name" : "mcyambu",
          "index" : 9,
          "offset" : 113,
          "literal" : "AM BUREAU",
          "type" : "Alphanumeric",
          "length" : 1,
          "scale" : 0,
          "delimiter" : 5,
          "usage" : "Optional",
          "debug" : false,
          "alwaysSent" : true,
          "compressed" : true
        },
        "mcytire" : {
          "name" : "mcytire",
          "index" : 10,
          "offset" : 117,
          "literal" : "TYRESIAS",
          "type" : "Alphanumeric",
          "length" : 1,
          "scale" : 0,
          "delimiter" : 10,
          "usage" : "Optional",
          "debug" : false,
          "alwaysSent" : true,
          "compressed" : true
        },
        "mcyvisa" : {
          "name" : "mcyvisa",
          "index" : 11,
          "offset" : 121,
          "literal" : "VISA",
          "type" : "Alphanumeric",
          "length" : 1,
          "scale" : 0,
          "delimiter" : 7,
          "usage" : "Optional",
          "debug" : false,
          "alwaysSent" : true,
          "compressed" : true
        },
        "cymello" : {
          "name" : "cymello",
          "index" : 12,
          "offset" : 125,
          "literal" : "MELLON BUREAU",
          "type" : "Alphanumeric",
          "length" : 1,
          "scale" : 0,
          "delimiter" : 23,
          "usage" : "Optional",
          "debug" : false,
          "alwaysSent" : true,
          "compressed" : true
        },
        "ilmcre" : {
          "name" : "ilmcre",
          "index" : 13,
          "offset" : 129,
          "literal" : "CREDIT LIMIT",
          "type" : "Numeric",
          "length" : 11,
          "scale" : 2,
          "delimiter" : 11,
          "usage" : "Optional",
          "debug" : false,
          "alwaysSent" : true,
          "compressed" : true
        },
        "ilcrea" : {
          "name" : "ilcrea",
          "index" : 14,
          "offset" : 143,
          "literal" : "PREVIOUS CREDIT",
          "type" : "Numeric",
          "length" : 11,
          "scale" : 2,
          "delimiter" : 12,
          "usage" : "Optional",
          "debug" : false,
          "alwaysSent" : true,
          "compressed" : true
        },
        "ilmcrt" : {
          "name" : "ilmcrt",
          "index" : 15,
          "offset" : 157,
          "literal" : "TEMPORAL CREDIT LIMI",
          "type" : "Numeric",
          "length" : 11,
          "scale" : 2,
          "delimiter" : 14,
          "usage" : "Optional",
          "debug" : false,
          "alwaysSent" : true,
          "compressed" : true
        },
        "ilimpe" : {
          "name" : "ilimpe",
          "index" : 16,
          "offset" : 171,
          "literal" : "CREDIT LIMI",
          "type" : "Numeric",
          "length" : 11,
          "scale" : 2,
          "delimiter" : 15,
          "usage" : "Optional",
          "debug" : false,
          "alwaysSent" : true,
          "compressed" : true
        },
        "fficra" : {
          "name" : "fficra",
          "index" : 17,
          "offset" : 185,
          "literal" : "VALID UNTIL",
          "type" : "Alphanumeric",
          "length" : 6,
          "scale" : 0,
          "delimiter" : 16,
          "usage" : "Optional",
          "debug" : false,
          "alwaysSent" : true,
          "compressed" : true
        },
        "fficrt" : {
          "name" : "fficrt",
          "index" : 18,
          "offset" : 194,
          "literal" : "VALID UNTIL",
          "type" : "Alphanumeric",
          "length" : 6,
          "scale" : 0,
          "delimiter" : 17,
          "usage" : "Optional",
          "debug" : false,
          "alwaysSent" : true,
          "compressed" : true
        },
        "ilcaad" : {
          "name" : "ilcaad",
          "index" : 19,
          "offset" : 203,
          "literal" : "CASH ADVANCE LIMIT",
          "type" : "Numeric",
          "length" : 11,
          "scale" : 2,
          "delimiter" : 21,
          "usage" : "Optional",
          "debug" : false,
          "alwaysSent" : true,
          "compressed" : true
        },
        "mctreas" : {
          "name" : "mctreas",
          "index" : 20,
          "offset" : 217,
          "literal" : "PENDING/REJECTION",
          "type" : "Alphanumeric",
          "length" : 2,
          "scale" : 0,
          "delimiter" : 18,
          "usage" : "Optional",
          "debug" : false,
          "alwaysSent" : true,
          "compressed" : true
        },
        "mctdesc" : {
          "name" : "mctdesc",
          "index" : 21,
          "offset" : 222,
          "literal" : "DESCRITPION REASON",
          "type" : "Alphanumeric",
          "length" : 15,
          "scale" : 0,
          "delimiter" : 19,
          "usage" : "Optional",
          "debug" : false,
          "alwaysSent" : true,
          "compressed" : true
        },
        "mctoffc" : {
          "name" : "mctoffc",
          "index" : 22,
          "offset" : 240,
          "literal" : "CREDIT OFFICER",
          "type" : "Alphanumeric",
          "length" : 8,
          "scale" : 0,
          "delimiter" : 20,
          "usage" : "Optional",
          "debug" : false,
          "alwaysSent" : true,
          "compressed" : true
        }
      }
    }
  }
}