{
  "name" : "ri00",
  "application" : "ri",
  "description" : "COLLECTIONS GENERAL MENU",
  "inputRecordName" : "rim000i",
  "sgAsPa" : false,
  "blankPaDiscarded" : false,
  "records" : {
    "rim000i" : {
      "name" : "rim000i",
      "transactionName" : "ri00",
      "description" : "NON-PAYMENT GENERAL MENU",
      "type" : "InputOutput",
      "source" : "FDF",
      "fields" : {
        "ropcion" : {
          "name" : "ropcion",
          "index" : 1,
          "offset" : 16,
          "literal" : "OPTION",
          "type" : "Numeric",
          "length" : 2,
          "scale" : 0,
          "delimiter" : 1,
          "usage" : "Optional",
          "debug" : true,
          "debugger" : "QR8CACN",
          "alwaysSent" : true,
          "compressed" : true
        },
        "rinocar" : {
          "name" : "rinocar",
          "index" : 2,
          "offset" : 21,
          "literal" : "CARD NUMBER",
          "type" : "Alphanumeric",
          "length" : 16,
          "scale" : 0,
          "delimiter" : 2,
          "usage" : "Optional",
          "debug" : true,
          "debugger" : "MR6CSEC1",
          "alwaysSent" : true,
          "compressed" : true
        },
        "rentcen" : {
          "name" : "rentcen",
          "index" : 3,
          "offset" : 40,
          "literal" : "C.A.C.",
          "type" : "Alphanumeric",
          "length" : 20,
          "scale" : 0,
          "delimiter" : 3,
          "usage" : "Optional",
          "debug" : true,
          "debugger" : "MR6CSEC0",
          "alwaysSent" : true,
          "compressed" : true
        },
        "rtacrea" : {
          "name" : "rtacrea",
          "index" : 4,
          "offset" : 63,
          "literal" : "TYPE (ACTION/REACT)",
          "type" : "Alphanumeric",
          "length" : 1,
          "scale" : 0,
          "delimiter" : 4,
          "usage" : "Optional",
          "debug" : false,
          "alwaysSent" : true,
          "compressed" : true
        },
        "rnumcli" : {
          "name" : "rnumcli",
          "index" : 5,
          "offset" : 67,
          "literal" : "CUSTOMER NO.",
          "type" : "Alphanumeric",
          "length" : 8,
          "scale" : 0,
          "delimiter" : 5,
          "usage" : "Optional",
          "debug" : true,
          "debugger" : "QR8CACN",
          "alwaysSent" : true,
          "compressed" : true
        },
        "rfigeex" : {
          "name" : "rfigeex",
          "index" : 6,
          "offset" : 78,
          "literal" : "DATE SINCE",
          "type" : "Alphanumeric",
          "length" : 8,
          "scale" : 0,
          "delimiter" : 6,
          "usage" : "Optional",
          "debug" : true,
          "debugger" : "QR8CFHA",
          "alwaysSent" : true,
          "compressed" : true
        },
        "rcodide" : {
          "name" : "rcodide",
          "index" : 7,
          "offset" : 89,
          "literal" : "ID /CTI",
          "type" : "Alphanumeric",
          "length" : 13,
          "scale" : 0,
          "delimiter" : 7,
          "usage" : "Optional",
          "debug" : false,
          "alwaysSent" : true,
          "compressed" : true
        },
        "rffgeex" : {
          "name" : "rffgeex",
          "index" : 8,
          "offset" : 105,
          "literal" : "DATE UNTIL",
          "type" : "Alphanumeric",
          "length" : 8,
          "scale" : 0,
          "delimiter" : 8,
          "usage" : "Optional",
          "debug" : true,
          "debugger" : "QR8CFHA",
          "alwaysSent" : true,
          "compressed" : true
        },
        "rcniges" : {
          "name" : "rcniges",
          "index" : 9,
          "offset" : 116,
          "literal" : "MANAGEMENT LEVEL",
          "type" : "Alphanumeric",
          "length" : 2,
          "scale" : 0,
          "delimiter" : 9,
          "usage" : "Optional",
          "debug" : false,
          "alwaysSent" : true,
          "compressed" : true
        },
        "rcgesto" : {
          "name" : "rcgesto",
          "index" : 10,
          "offset" : 121,
          "literal" : "CONSULTANT CODE",
          "type" : "Alphanumeric",
          "length" : 4,
          "scale" : 0,
          "delimiter" : 10,
          "usage" : "Optional",
          "debug" : false,
          "alwaysSent" : true,
          "compressed" : true
        },
        "rbillin" : {
          "name" : "rbillin",
          "index" : 11,
          "offset" : 128,
          "literal" : "BILLING PERIOD",
          "type" : "Alphanumeric",
          "length" : 5,
          "scale" : 0,
          "delimiter" : 11,
          "usage" : "Optional",
          "debug" : false,
          "alwaysSent" : true,
          "compressed" : true
        },
        "rimpdeu" : {
          "name" : "rimpdeu",
          "index" : 12,
          "offset" : 136,
          "literal" : "MINIMUM AMOUNT",
          "type" : "Edit",
          "length" : 13,
          "scale" : 2,
          "delimiter" : 12,
          "usage" : "Optional",
          "debug" : false,
          "debugger" : "QR8CACN",
          "alwaysSent" : true,
          "compressed" : true
        },
        "rcacrea" : {
          "name" : "rcacrea",
          "index" : 13,
          "offset" : 152,
          "literal" : "ACTION/REACTION CODE",
          "type" : "Alphanumeric",
          "length" : 3,
          "scale" : 0,
          "delimiter" : 13,
          "usage" : "Optional",
          "debug" : false,
          "alwaysSent" : true,
          "compressed" : true
        },
        "rcsubpr" : {
          "name" : "rcsubpr",
          "index" : 14,
          "offset" : 158,
          "literal" : "SUBPRODUCT",
          "type" : "Alphanumeric",
          "length" : 4,
          "scale" : 0,
          "delimiter" : 15,
          "usage" : "Optional",
          "debug" : false,
          "alwaysSent" : true,
          "compressed" : true
        },
        "rirecup" : {
          "name" : "rirecup",
          "index" : 15,
          "offset" : 165,
          "literal" : "MAXIMUM AMOUNT",
          "type" : "Edit",
          "length" : 13,
          "scale" : 2,
          "delimiter" : 14,
          "usage" : "Optional",
          "debug" : false,
          "debugger" : "QR8CACN",
          "alwaysSent" : true,
          "compressed" : true
        },
        "rcodgar" : {
          "name" : "rcodgar",
          "index" : 16,
          "offset" : 181,
          "literal" : "GUARANTEE",
          "type" : "Alphanumeric",
          "length" : 6,
          "scale" : 0,
          "delimiter" : 21,
          "usage" : "Optional",
          "debug" : false,
          "alwaysSent" : true,
          "compressed" : true
        },
        "rbildat" : {
          "name" : "rbildat",
          "index" : 17,
          "offset" : 190,
          "literal" : "BILLING DAY",
          "type" : "Alphanumeric",
          "length" : 2,
          "scale" : 0,
          "delimiter" : 22,
          "usage" : "Optional",
          "debug" : false,
          "alwaysSent" : true,
          "compressed" : true
        },
        "ruserid" : {
          "name" : "ruserid",
          "index" : 18,
          "offset" : 195,
          "literal" : "USERID",
          "type" : "Alphanumeric",
          "length" : 8,
          "scale" : 0,
          "delimiter" : 16,
          "usage" : "Output",
          "debug" : false,
          "alwaysSent" : true,
          "compressed" : true
        },
        "rgestor" : {
          "name" : "rgestor",
          "index" : 19,
          "offset" : 206,
          "literal" : "COLLECTOR CODE",
          "type" : "Alphanumeric",
          "length" : 4,
          "scale" : 0,
          "delimiter" : 17,
          "usage" : "Output",
          "debug" : false,
          "alwaysSent" : true,
          "compressed" : true
        },
        "rproduc" : {
          "name" : "rproduc",
          "index" : 20,
          "offset" : 213,
          "literal" : "PRODUCT CODE",
          "type" : "Alphanumeric",
          "length" : 2,
          "scale" : 0,
          "delimiter" : 18,
          "usage" : "Output",
          "debug" : false,
          "alwaysSent" : true,
          "compressed" : true
        },
        "rflag1" : {
          "name" : "rflag1",
          "index" : 21,
          "offset" : 218,
          "literal" : "COLLECTOR FLAG",
          "type" : "Alphanumeric",
          "length" : 1,
          "scale" : 0,
          "delimiter" : 19,
          "usage" : "Output",
          "debug" : false,
          "alwaysSent" : true,
          "compressed" : true
        },
        "rflag2" : {
          "name" : "rflag2",
          "index" : 22,
          "offset" : 222,
          "literal" : "ACCEL LEVEL",
          "type" : "Alphanumeric",
          "length" : 1,
          "scale" : 0,
          "delimiter" : 20,
          "usage" : "Output",
          "debug" : false,
          "alwaysSent" : true,
          "compressed" : true
        }
      }
    }
  }
}