{
  "name" : "u704",
  "application" : "ug",
  "description" : "CREATING OF INVOICING EXCEPTIONS",
  "inputRecordName" : "ugm120",
  "sgAsPa" : false,
  "blankPaDiscarded" : false,
  "records" : {
    "ugm120" : {
      "name" : "ugm120",
      "transactionName" : "u704",
      "description" : "CREATING OF INVOICING",
      "type" : "Input",
      "source" : "FDF",
      "fields" : {
        "ccc" : {
          "name" : "ccc",
          "index" : 1,
          "offset" : 16,
          "literal" : "LOAN NUMBER",
          "type" : "Alphanumeric",
          "length" : 20,
          "scale" : 0,
          "delimiter" : 1,
          "usage" : "Required",
          "debug" : false,
          "alwaysSent" : true,
          "compressed" : true
        },
        "fvalor" : {
          "name" : "fvalor",
          "index" : 2,
          "offset" : 39,
          "literal" : "FECHA VALOR INCIDENC",
          "type" : "Alphanumeric",
          "length" : 8,
          "scale" : 0,
          "delimiter" : 2,
          "usage" : "Output",
          "debug" : true,
          "debugger" : "QR8CFHA",
          "alwaysSent" : true,
          "compressed" : true
        },
        "tincid" : {
          "name" : "tincid",
          "index" : 3,
          "offset" : 50,
          "literal" : "TIPO DE INCIDENCIA",
          "type" : "Alphanumeric",
          "length" : 1,
          "scale" : 0,
          "delimiter" : 3,
          "usage" : "Output",
          "debug" : false,
          "alwaysSent" : true,
          "compressed" : true
        },
        "taccio" : {
          "name" : "taccio",
          "index" : 4,
          "offset" : 54,
          "literal" : "TIPO DE ACCION",
          "type" : "Alphanumeric",
          "length" : 1,
          "scale" : 0,
          "delimiter" : 4,
          "usage" : "Output",
          "debug" : false,
          "alwaysSent" : true,
          "compressed" : true
        },
        "nroinc" : {
          "name" : "nroinc",
          "index" : 5,
          "offset" : 58,
          "literal" : "NUMERO DE INCIDENCIA",
          "type" : "Numeric",
          "length" : 4,
          "scale" : 0,
          "delimiter" : 5,
          "usage" : "Output",
          "debug" : true,
          "debugger" : "QR8CACN",
          "alwaysSent" : true,
          "compressed" : true
        },
        "import" : {
          "name" : "import",
          "index" : 6,
          "offset" : 65,
          "literal" : "IMPORTE INCIDENCIA",
          "type" : "Numeric",
          "length" : 15,
          "scale" : 3,
          "delimiter" : 6,
          "usage" : "Output",
          "debug" : true,
          "debugger" : "QR8CACN",
          "alwaysSent" : true,
          "compressed" : true
        },
        "icomis" : {
          "name" : "icomis",
          "index" : 7,
          "offset" : 83,
          "literal" : "IMPORTE COMISION",
          "type" : "Numeric",
          "length" : 15,
          "scale" : 3,
          "delimiter" : 7,
          "usage" : "Output",
          "debug" : true,
          "debugger" : "QR8CACN",
          "alwaysSent" : true,
          "compressed" : true
        },
        "camort" : {
          "name" : "camort",
          "index" : 8,
          "offset" : 101,
          "literal" : "TIPO DE AMORTIZACION",
          "type" : "Alphanumeric",
          "length" : 1,
          "scale" : 0,
          "delimiter" : 8,
          "usage" : "Output",
          "debug" : false,
          "alwaysSent" : true,
          "compressed" : true
        },
        "nrebsu" : {
          "name" : "nrebsu",
          "index" : 9,
          "offset" : 105,
          "literal" : "NUM. REC. SUPRIMIDOS",
          "type" : "Numeric",
          "length" : 4,
          "scale" : 0,
          "delimiter" : 9,
          "usage" : "Output",
          "debug" : true,
          "debugger" : "QR8CACN",
          "alwaysSent" : true,
          "compressed" : true
        },
        "pinnou" : {
          "name" : "pinnou",
          "index" : 10,
          "offset" : 112,
          "literal" : "NUEVO TIPO INTERES",
          "type" : "Numeric",
          "length" : 9,
          "scale" : 6,
          "delimiter" : 10,
          "usage" : "Output",
          "debug" : true,
          "debugger" : "QR8CACN",
          "alwaysSent" : true,
          "compressed" : true
        },
        "fpgnou" : {
          "name" : "fpgnou",
          "index" : 11,
          "offset" : 124,
          "literal" : "NUEVA F. P.PAG.CAP.",
          "type" : "Alphanumeric",
          "length" : 8,
          "scale" : 0,
          "delimiter" : 11,
          "usage" : "Output",
          "debug" : true,
          "debugger" : "QR8CFHA",
          "alwaysSent" : true,
          "compressed" : true
        },
        "nplpen" : {
          "name" : "nplpen",
          "index" : 12,
          "offset" : 135,
          "literal" : "NUEVO PLAZO",
          "type" : "Numeric",
          "length" : 4,
          "scale" : 0,
          "delimiter" : 12,
          "usage" : "Required",
          "debug" : true,
          "debugger" : "QR8CACN",
          "alwaysSent" : true,
          "compressed" : true
        },
        "tfmnou" : {
          "name" : "tfmnou",
          "index" : 13,
          "offset" : 142,
          "literal" : "NUEVA FORMULA",
          "type" : "Alphanumeric",
          "length" : 1,
          "scale" : 0,
          "delimiter" : 13,
          "usage" : "Output",
          "debug" : false,
          "alwaysSent" : true,
          "compressed" : true
        },
        "qpgnou" : {
          "name" : "qpgnou",
          "index" : 14,
          "offset" : 146,
          "literal" : "NUEVA RAZON PROGRES.",
          "type" : "Numeric",
          "length" : 10,
          "scale" : 7,
          "delimiter" : 14,
          "usage" : "Output",
          "debug" : true,
          "debugger" : "QR8CACN",
          "alwaysSent" : true,
          "compressed" : true
        },
        "tvnnou" : {
          "name" : "tvnnou",
          "index" : 15,
          "offset" : 159,
          "literal" : "NUEVO TIPO VENCIMIEN",
          "type" : "Alphanumeric",
          "length" : 1,
          "scale" : 0,
          "delimiter" : 15,
          "usage" : "Output",
          "debug" : false,
          "alwaysSent" : true,
          "compressed" : true
        },
        "ugyimpr" : {
          "name" : "ugyimpr",
          "index" : 16,
          "offset" : 163,
          "literal" : "IMPRIMIR RECIBO(S/N)",
          "type" : "Alphanumeric",
          "length" : 1,
          "scale" : 0,
          "delimiter" : 16,
          "usage" : "Output",
          "debug" : false,
          "alwaysSent" : true,
          "compressed" : true
        }
      }
    },
    "ugm121" : {
      "name" : "ugm121",
      "transactionName" : "u704",
      "description" : "BILL EXCEPTIONS CREATION",
      "type" : "Output",
      "source" : "FDF",
      "fields" : {
        "taccio" : {
          "name" : "taccio",
          "index" : 1,
          "offset" : 16,
          "literal" : "ACTION MADE",
          "type" : "Alphanumeric",
          "length" : 5,
          "scale" : 0,
          "delimiter" : 1,
          "usage" : "Output",
          "debug" : false,
          "alwaysSent" : false,
          "compressed" : true
        },
        "nroinc" : {
          "name" : "nroinc",
          "index" : 2,
          "offset" : 24,
          "literal" : "EXCEPTION NUMBER",
          "type" : "Numeric",
          "length" : 4,
          "scale" : 0,
          "delimiter" : 2,
          "usage" : "Output",
          "debug" : false,
          "alwaysSent" : false,
          "compressed" : true
        },
        "tincid" : {
          "name" : "tincid",
          "index" : 3,
          "offset" : 31,
          "literal" : "EXCEPTION TYPE",
          "type" : "Alphanumeric",
          "length" : 1,
          "scale" : 0,
          "delimiter" : 3,
          "usage" : "Output",
          "debug" : false,
          "alwaysSent" : false,
          "compressed" : true
        },
        "fvalor" : {
          "name" : "fvalor",
          "index" : 4,
          "offset" : 35,
          "literal" : "EXCEPTION VALUE DATE",
          "type" : "Alphanumeric",
          "length" : 10,
          "scale" : 0,
          "delimiter" : 4,
          "usage" : "Output",
          "debug" : false,
          "alwaysSent" : false,
          "compressed" : true
        }
      }
    },
    "ugm122" : {
      "name" : "ugm122",
      "transactionName" : "u704",
      "description" : "EXCEPTION VALUE DATE",
      "type" : "Output",
      "source" : "FDF",
      "fields" : {
        "ugfoper" : {
          "name" : "ugfoper",
          "index" : 1,
          "offset" : 16,
          "literal" : "ACTION MADE",
          "type" : "Alphanumeric",
          "length" : 10,
          "scale" : 0,
          "delimiter" : 1,
          "usage" : "Output",
          "debug" : false,
          "alwaysSent" : false,
          "compressed" : true
        },
        "ugfvalo" : {
          "name" : "ugfvalo",
          "index" : 2,
          "offset" : 29,
          "literal" : "EXCEPTION NUMBER",
          "type" : "Numeric",
          "length" : 10,
          "scale" : 0,
          "delimiter" : 2,
          "usage" : "Output",
          "debug" : false,
          "alwaysSent" : false,
          "compressed" : true
        },
        "ugpinan" : {
          "name" : "ugpinan",
          "index" : 3,
          "offset" : 42,
          "literal" : "EXCEPTION TYPE",
          "type" : "Alphanumeric",
          "length" : 10,
          "scale" : 0,
          "delimiter" : 3,
          "usage" : "Output",
          "debug" : false,
          "alwaysSent" : false,
          "compressed" : true
        },
        "ugpinno" : {
          "name" : "ugpinno",
          "index" : 4,
          "offset" : 55,
          "literal" : "EXCEPTION VALUE DATE",
          "type" : "Alphanumeric",
          "length" : 10,
          "scale" : 0,
          "delimiter" : 4,
          "usage" : "Output",
          "debug" : false,
          "alwaysSent" : false,
          "compressed" : true
        },
        "ugyanul" : {
          "name" : "ugyanul",
          "index" : 5,
          "offset" : 68,
          "literal" : "ANNULL.IND.",
          "type" : "Alphanumeric",
          "length" : 3,
          "scale" : 0,
          "delimiter" : 5,
          "usage" : "Output",
          "debug" : false,
          "alwaysSent" : false,
          "compressed" : true
        }
      }
    },
    "ugm123" : {
      "name" : "ugm123",
      "transactionName" : "u704",
      "description" : "INT.RATE CHANGE BILL EXCEPTIO",
      "type" : "Output",
      "source" : "FDF",
      "fields" : { }
    },
    "ugm126" : {
      "name" : "ugm126",
      "transactionName" : "u704",
      "description" : "U704 VOUCHER",
      "type" : "Output",
      "source" : "FDF",
      "fields" : {
        "date" : {
          "name" : "date",
          "index" : 1,
          "offset" : 16,
          "literal" : "ACCOUNTING DATE",
          "type" : "Alphanumeric",
          "length" : 10,
          "scale" : 0,
          "delimiter" : 1,
          "usage" : "Output",
          "debug" : false,
          "alwaysSent" : false,
          "compressed" : true
        },
        "applnum" : {
          "name" : "applnum",
          "index" : 2,
          "offset" : 29,
          "literal" : "APPLICATION NUMBER",
          "type" : "Numeric",
          "length" : 15,
          "scale" : 0,
          "delimiter" : 2,
          "usage" : "Output",
          "debug" : false,
          "alwaysSent" : false,
          "compressed" : true
        },
        "entity" : {
          "name" : "entity",
          "index" : 3,
          "offset" : 47,
          "literal" : "CCC ENTITY",
          "type" : "Alphanumeric",
          "length" : 4,
          "scale" : 0,
          "delimiter" : 3,
          "usage" : "Output",
          "debug" : false,
          "alwaysSent" : false,
          "compressed" : true
        },
        "branch" : {
          "name" : "branch",
          "index" : 4,
          "offset" : 54,
          "literal" : "CCC BRANCH",
          "type" : "Alphanumeric",
          "length" : 4,
          "scale" : 0,
          "delimiter" : 4,
          "usage" : "Output",
          "debug" : false,
          "alwaysSent" : false,
          "compressed" : true
        },
        "cd" : {
          "name" : "cd",
          "index" : 5,
          "offset" : 61,
          "literal" : "CCC CHECK DIGITS",
          "type" : "Alphanumeric",
          "length" : 2,
          "scale" : 0,
          "delimiter" : 5,
          "usage" : "Output",
          "debug" : false,
          "alwaysSent" : false,
          "compressed" : true
        },
        "account" : {
          "name" : "account",
          "index" : 6,
          "offset" : 66,
          "literal" : "CCC ACCOUNT",
          "type" : "Alphanumeric",
          "length" : 10,
          "scale" : 0,
          "delimiter" : 6,
          "usage" : "Output",
          "debug" : false,
          "alwaysSent" : false,
          "compressed" : true
        },
        "debtor" : {
          "name" : "debtor",
          "index" : 7,
          "offset" : 79,
          "literal" : "DEBTOR NAME",
          "type" : "Alphanumeric",
          "length" : 30,
          "scale" : 0,
          "delimiter" : 7,
          "usage" : "Output",
          "debug" : false,
          "alwaysSent" : false,
          "compressed" : true
        },
        "unexp" : {
          "name" : "unexp",
          "index" : 8,
          "offset" : 112,
          "literal" : "UNEXPIRED AMOUNT",
          "type" : "Alphanumeric",
          "length" : 20,
          "scale" : 0,
          "delimiter" : 8,
          "usage" : "Output",
          "debug" : false,
          "alwaysSent" : false,
          "compressed" : true
        },
        "unexpcu" : {
          "name" : "unexpcu",
          "index" : 9,
          "offset" : 135,
          "literal" : "UNEXPIRED AMOUNT CUR",
          "type" : "Alphanumeric",
          "length" : 3,
          "scale" : 0,
          "delimiter" : 9,
          "usage" : "Output",
          "debug" : false,
          "alwaysSent" : false,
          "compressed" : true
        },
        "inidur" : {
          "name" : "inidur",
          "index" : 10,
          "offset" : 141,
          "literal" : "INITIAL DURATION",
          "type" : "Alphanumeric",
          "length" : 3,
          "scale" : 0,
          "delimiter" : 10,
          "usage" : "Output",
          "debug" : false,
          "alwaysSent" : false,
          "compressed" : true
        },
        "remdur" : {
          "name" : "remdur",
          "index" : 11,
          "offset" : 147,
          "literal" : "REMAINING DURATION",
          "type" : "Alphanumeric",
          "length" : 3,
          "scale" : 0,
          "delimiter" : 11,
          "usage" : "Output",
          "debug" : false,
          "alwaysSent" : false,
          "compressed" : true
        },
        "cquot" : {
          "name" : "cquot",
          "index" : 12,
          "offset" : 153,
          "literal" : "CURRENT QUOTA",
          "type" : "Alphanumeric",
          "length" : 20,
          "scale" : 0,
          "delimiter" : 12,
          "usage" : "Output",
          "debug" : false,
          "alwaysSent" : false,
          "compressed" : true
        },
        "cquotcu" : {
          "name" : "cquotcu",
          "index" : 13,
          "offset" : 176,
          "literal" : "CURRENT QUOTA CUR",
          "type" : "Alphanumeric",
          "length" : 3,
          "scale" : 0,
          "delimiter" : 13,
          "usage" : "Output",
          "debug" : false,
          "alwaysSent" : false,
          "compressed" : true
        },
        "newdur" : {
          "name" : "newdur",
          "index" : 14,
          "offset" : 182,
          "literal" : "NEW DURATION",
          "type" : "Alphanumeric",
          "length" : 3,
          "scale" : 0,
          "delimiter" : 14,
          "usage" : "Output",
          "debug" : false,
          "alwaysSent" : false,
          "compressed" : true
        },
        "nquot" : {
          "name" : "nquot",
          "index" : 15,
          "offset" : 188,
          "literal" : "NEW QUOTA",
          "type" : "Alphanumeric",
          "length" : 20,
          "scale" : 0,
          "delimiter" : 15,
          "usage" : "Output",
          "debug" : false,
          "alwaysSent" : false,
          "compressed" : true
        },
        "nquotcu" : {
          "name" : "nquotcu",
          "index" : 16,
          "offset" : 211,
          "literal" : "NEW QUOTA CURRENCY",
          "type" : "Alphanumeric",
          "length" : 3,
          "scale" : 0,
          "delimiter" : 16,
          "usage" : "Output",
          "debug" : false,
          "alwaysSent" : false,
          "compressed" : true
        },
        "npaydt" : {
          "name" : "npaydt",
          "index" : 17,
          "offset" : 217,
          "literal" : "NEW PAYMENT DATE",
          "type" : "Alphanumeric",
          "length" : 10,
          "scale" : 0,
          "delimiter" : 17,
          "usage" : "Output",
          "debug" : false,
          "alwaysSent" : false,
          "compressed" : true
        }
      }
    }
  },
  "inputRecord" : {
    "name" : "ugm120",
    "transactionName" : "u704",
    "description" : "CREATING OF INVOICING",
    "type" : "Input",
    "source" : "FDF",
    "fields" : {
      "ccc" : {
        "name" : "ccc",
        "index" : 1,
        "offset" : 16,
        "literal" : "LOAN NUMBER",
        "type" : "Alphanumeric",
        "length" : 20,
        "scale" : 0,
        "delimiter" : 1,
        "usage" : "Required",
        "debug" : false,
        "alwaysSent" : true,
        "compressed" : true
      },
      "fvalor" : {
        "name" : "fvalor",
        "index" : 2,
        "offset" : 39,
        "literal" : "FECHA VALOR INCIDENC",
        "type" : "Alphanumeric",
        "length" : 8,
        "scale" : 0,
        "delimiter" : 2,
        "usage" : "Output",
        "debug" : true,
        "debugger" : "QR8CFHA",
        "alwaysSent" : true,
        "compressed" : true
      },
      "tincid" : {
        "name" : "tincid",
        "index" : 3,
        "offset" : 50,
        "literal" : "TIPO DE INCIDENCIA",
        "type" : "Alphanumeric",
        "length" : 1,
        "scale" : 0,
        "delimiter" : 3,
        "usage" : "Output",
        "debug" : false,
        "alwaysSent" : true,
        "compressed" : true
      },
      "taccio" : {
        "name" : "taccio",
        "index" : 4,
        "offset" : 54,
        "literal" : "TIPO DE ACCION",
        "type" : "Alphanumeric",
        "length" : 1,
        "scale" : 0,
        "delimiter" : 4,
        "usage" : "Output",
        "debug" : false,
        "alwaysSent" : true,
        "compressed" : true
      },
      "nroinc" : {
        "name" : "nroinc",
        "index" : 5,
        "offset" : 58,
        "literal" : "NUMERO DE INCIDENCIA",
        "type" : "Numeric",
        "length" : 4,
        "scale" : 0,
        "delimiter" : 5,
        "usage" : "Output",
        "debug" : true,
        "debugger" : "QR8CACN",
        "alwaysSent" : true,
        "compressed" : true
      },
      "import" : {
        "name" : "import",
        "index" : 6,
        "offset" : 65,
        "literal" : "IMPORTE INCIDENCIA",
        "type" : "Numeric",
        "length" : 15,
        "scale" : 3,
        "delimiter" : 6,
        "usage" : "Output",
        "debug" : true,
        "debugger" : "QR8CACN",
        "alwaysSent" : true,
        "compressed" : true
      },
      "icomis" : {
        "name" : "icomis",
        "index" : 7,
        "offset" : 83,
        "literal" : "IMPORTE COMISION",
        "type" : "Numeric",
        "length" : 15,
        "scale" : 3,
        "delimiter" : 7,
        "usage" : "Output",
        "debug" : true,
        "debugger" : "QR8CACN",
        "alwaysSent" : true,
        "compressed" : true
      },
      "camort" : {
        "name" : "camort",
        "index" : 8,
        "offset" : 101,
        "literal" : "TIPO DE AMORTIZACION",
        "type" : "Alphanumeric",
        "length" : 1,
        "scale" : 0,
        "delimiter" : 8,
        "usage" : "Output",
        "debug" : false,
        "alwaysSent" : true,
        "compressed" : true
      },
      "nrebsu" : {
        "name" : "nrebsu",
        "index" : 9,
        "offset" : 105,
        "literal" : "NUM. REC. SUPRIMIDOS",
        "type" : "Numeric",
        "length" : 4,
        "scale" : 0,
        "delimiter" : 9,
        "usage" : "Output",
        "debug" : true,
        "debugger" : "QR8CACN",
        "alwaysSent" : true,
        "compressed" : true
      },
      "pinnou" : {
        "name" : "pinnou",
        "index" : 10,
        "offset" : 112,
        "literal" : "NUEVO TIPO INTERES",
        "type" : "Numeric",
        "length" : 9,
        "scale" : 6,
        "delimiter" : 10,
        "usage" : "Output",
        "debug" : true,
        "debugger" : "QR8CACN",
        "alwaysSent" : true,
        "compressed" : true
      },
      "fpgnou" : {
        "name" : "fpgnou",
        "index" : 11,
        "offset" : 124,
        "literal" : "NUEVA F. P.PAG.CAP.",
        "type" : "Alphanumeric",
        "length" : 8,
        "scale" : 0,
        "delimiter" : 11,
        "usage" : "Output",
        "debug" : true,
        "debugger" : "QR8CFHA",
        "alwaysSent" : true,
        "compressed" : true
      },
      "nplpen" : {
        "name" : "nplpen",
        "index" : 12,
        "offset" : 135,
        "literal" : "NUEVO PLAZO",
        "type" : "Numeric",
        "length" : 4,
        "scale" : 0,
        "delimiter" : 12,
        "usage" : "Required",
        "debug" : true,
        "debugger" : "QR8CACN",
        "alwaysSent" : true,
        "compressed" : true
      },
      "tfmnou" : {
        "name" : "tfmnou",
        "index" : 13,
        "offset" : 142,
        "literal" : "NUEVA FORMULA",
        "type" : "Alphanumeric",
        "length" : 1,
        "scale" : 0,
        "delimiter" : 13,
        "usage" : "Output",
        "debug" : false,
        "alwaysSent" : true,
        "compressed" : true
      },
      "qpgnou" : {
        "name" : "qpgnou",
        "index" : 14,
        "offset" : 146,
        "literal" : "NUEVA RAZON PROGRES.",
        "type" : "Numeric",
        "length" : 10,
        "scale" : 7,
        "delimiter" : 14,
        "usage" : "Output",
        "debug" : true,
        "debugger" : "QR8CACN",
        "alwaysSent" : true,
        "compressed" : true
      },
      "tvnnou" : {
        "name" : "tvnnou",
        "index" : 15,
        "offset" : 159,
        "literal" : "NUEVO TIPO VENCIMIEN",
        "type" : "Alphanumeric",
        "length" : 1,
        "scale" : 0,
        "delimiter" : 15,
        "usage" : "Output",
        "debug" : false,
        "alwaysSent" : true,
        "compressed" : true
      },
      "ugyimpr" : {
        "name" : "ugyimpr",
        "index" : 16,
        "offset" : 163,
        "literal" : "IMPRIMIR RECIBO(S/N)",
        "type" : "Alphanumeric",
        "length" : 1,
        "scale" : 0,
        "delimiter" : 16,
        "usage" : "Output",
        "debug" : false,
        "alwaysSent" : true,
        "compressed" : true
      }
    }
  }
}